AUTHORS.rst
CHANGES.rst
CONTRIBUTING.rst
INSTALL.rst
LICENSE
MANIFEST.in
README.rst
RELEASE-NOTES.rst
babel.ini
pytest.ini
run-tests.sh
setup.cfg
setup.py
docs/Makefile
docs/api.rst
docs/authors.rst
docs/changes.rst
docs/conf.py
docs/contributing.rst
docs/index.rst
docs/installation.rst
docs/license.rst
docs/make.bat
docs/usage.rst
invenio_trends_ui/__init__.py
invenio_trends_ui/bundles.py
invenio_trends_ui/config.py
invenio_trends_ui/ext.py
invenio_trends_ui/version.py
invenio_trends_ui/views.py
invenio_trends_ui.egg-info/PKG-INFO
invenio_trends_ui.egg-info/SOURCES.txt
invenio_trends_ui.egg-info/dependency_links.txt
invenio_trends_ui.egg-info/entry_points.txt
invenio_trends_ui.egg-info/not-zip-safe
invenio_trends_ui.egg-info/requires.txt
invenio_trends_ui.egg-info/top_level.txt
invenio_trends_ui/static/js/invenio_trends_ui/app.js
invenio_trends_ui/static/js/invenio_trends_ui/trends.directives.js
invenio_trends_ui/static/js/invenio_trends_ui/trends.module.js
invenio_trends_ui/static/js/invenio_trends_ui/trends.services.js
invenio_trends_ui/static/js/invenio_trends_ui/trends.vis.js
invenio_trends_ui/static/js/invenio_trends_ui/templates/dashboard.html
invenio_trends_ui/static/scss/invenio_trends_ui/trends.scss
invenio_trends_ui/templates/invenio_trends_ui/base.html
invenio_trends_ui/templates/invenio_trends_ui/base_header.html
invenio_trends_ui/templates/invenio_trends_ui/dashboard.html
invenio_trends_ui/templates/invenio_trends_ui/header.html
invenio_trends_ui/translations/fr/LC_MESSAGES/messages.po
tests/conftest.py
tests/test_invenio_search_ui.py