Metadata-Version: 1.1
Name: invenio-trends-ui
Version: 1.0.0a1
Summary: UI for Invenio-Search.
Home-page: https://github.com/inveniosoftware/invenio-trends-ui
Author: CERN
Author-email: info@inveniosoftware.org
License: GPLv2
Keywords: invenio TODO
Platform: any
Classifier: Environment :: Web Environment
Classifier: Intended Audience :: Developers
Classifier: License :: OSI Approved :: GNU General Public License v2 (GPLv2)
Classifier: Operating System :: OS Independent
Classifier: Programming Language :: Python
Classifier: Topic :: Internet :: WWW/HTTP :: Dynamic Content
Classifier: Topic :: Software Development :: Libraries :: Python Modules
Classifier: Programming Language :: Python :: 2
Classifier: Programming Language :: Python :: 2.7
Classifier: Programming Language :: Python :: 3
Classifier: Programming Language :: Python :: 3.3
Classifier: Programming Language :: Python :: 3.4
Classifier: Programming Language :: Python :: 3.5
Classifier: Development Status :: 1 - Planning
